darshellclock/__init__.py
darshellclock/__main__.py
darshellclock/cfg.py
darshellclock/clock.py
darshellclock/globals.py
darshellclock/help.py
darshellclock/main.py
darshellclock/utils.py
darshellclock-1.1.2.dist-info/LICENSE
darshellclock-1.1.2.dist-info/METADATA
darshellclock-1.1.2.dist-info/WHEEL
darshellclock-1.1.2.dist-info/entry_points.txt
darshellclock-1.1.2.dist-info/top_level.txt
darshellclock-1.1.2.dist-info/RECORD
