Metadata-Version: 2.1
Name: darshellclock
Version: 1.1.2
Summary: Minimalist terminal digital clock
Home-page: https://github.com/darokin/darshell-clock
Author: Adrien Rebuzzi (darokin)
Author-email: darokin42@gmail.com
License: UNKNOWN
Platform: UNKNOWN
Classifier: Programming Language :: Python :: 3
Classifier: License :: OSI Approved :: MIT License
Classifier: Operating System :: OS Independent
Requires-Python: >=3.6.0
Requires-Dist: windows-curses (>=2.0) ; platform_system == "Windows"
